dnac/__init__.py
dnac/basicauth.py
dnac/client.py
dnac/commandrunner.py
dnac/commandrunner_task.py
dnac/config_archive.py
dnac/config_archive_settings.py
dnac/crud.py
dnac/ctype.py
dnac/deployment.py
dnac/device_archive.py
dnac/device_archive_task.py
dnac/dnac.py
dnac/dnac_config.py
dnac/dnacapi.py
dnac/file.py
dnac/networkdevice.py
dnac/project.py
dnac/site.py
dnac/site_hierarchy.py
dnac/task.py
dnac/template.py
dnac/timestamp.py
dnac/version.py
dnac/xauthtoken.py
dnac-1.3.1.7.dist-info/LICENSE
dnac-1.3.1.7.dist-info/METADATA
dnac-1.3.1.7.dist-info/WHEEL
dnac-1.3.1.7.dist-info/top_level.txt
dnac-1.3.1.7.dist-info/RECORD
