Metadata-Version: 2.1
Name: dnac
Version: 1.3.1.7
Summary: A wrapper for using Cisco DNA Center's REST API
Home-page: https://developer.cisco.com/codeexchange/github/repo/rsayle/DNAC-Python-Wrapper
Author: Robert Sayle
Author-email: rsayle@cisco.com
License: UNKNOWN
Platform: UNKNOWN
Classifier: Development Status :: 3 - Alpha
Classifier: Programming Language :: Python :: 3
Classifier: License :: Other/Proprietary License
Classifier: Operating System :: OS Independent
Classifier: Topic :: System :: Networking
Classifier: Topic :: Utilities
Classifier: Intended Audience :: Information Technology
Classifier: Intended Audience :: Telecommunications Industry
Requires-Python: >=3
Requires-Dist: requests
Requires-Dist: multi-key-dict
